README.md
pyproject.toml
src/lccommon/__init__.py
src/lccommon/net_util.py
src/lccommon/spice_parser.py
src/lclayout/__init__.py
src/lclayout/data_types.py
src/lclayout/extrema.py
src/lclayout/router.py
src/lclayout/routing_graph.py
src/lclayout/standalone.py
src/lclayout/tech_util.py
src/lclayout.egg-info/PKG-INFO
src/lclayout.egg-info/SOURCES.txt
src/lclayout.egg-info/dependency_links.txt
src/lclayout.egg-info/entry_points.txt
src/lclayout.egg-info/requires.txt
src/lclayout.egg-info/top_level.txt
src/lclayout/drc_cleaner/__init__.py
src/lclayout/drc_cleaner/base.py
src/lclayout/drc_cleaner/drc_cleaner.py
src/lclayout/drc_cleaner/drc_theorem_proofs.py
src/lclayout/drc_cleaner/standalone.py
src/lclayout/graphrouter/__init__.py
src/lclayout/graphrouter/graphrouter.py
src/lclayout/graphrouter/hv_router.py
src/lclayout/graphrouter/lp_router.py
src/lclayout/graphrouter/min_area_router.py
src/lclayout/graphrouter/multi_via_router.py
src/lclayout/graphrouter/pathfinder.py
src/lclayout/graphrouter/pyo3_graphrouter.py
src/lclayout/graphrouter/signal_router.py
src/lclayout/graphrouter/smt_router.py
src/lclayout/layout/__init__.py
src/lclayout/layout/cell_template.py
src/lclayout/layout/geometry_helpers.py
src/lclayout/layout/grid.py
src/lclayout/layout/grid_helpers.py
src/lclayout/layout/layers.py
src/lclayout/layout/notch_removal.py
src/lclayout/layout/transistor.py
src/lclayout/layout/welltap.py
src/lclayout/lef/__init__.py
src/lclayout/lef/types.py
src/lclayout/lvs/__init__.py
src/lclayout/lvs/lvs.py
src/lclayout/place/__init__.py
src/lclayout/place/euler_placer.py
src/lclayout/place/eulertours.py
src/lclayout/place/meta_placer.py
src/lclayout/place/partition.py
src/lclayout/place/place.py
src/lclayout/place/smt_placer.py
src/lclayout/writer/__init__.py
src/lclayout/writer/gds_writer.py
src/lclayout/writer/lef_writer.py
src/lclayout/writer/magic_writer.py
src/lclayout/writer/oasis_writer.py
src/lclayout/writer/writer.py