Metadata-Version: 2.1
Name: lclayout
Version: 0.0.18
Summary: CMOS standard-cell layout generator.
Author-email: "T. Kramer" <code@tkramer.ch>
License: OHL-S v2.0
Project-URL: Homepage, https://codeberg.org/librecell/lclayout
Project-URL: Repository, https://codeberg.org/librecell/lclayout
Project-URL: Issue Tracker, https://codeberg.org/librecell/lclayout/issues
Keywords: cmos,cell,layout,generator,klayout,vlsi,asic
Classifier: Development Status :: 3 - Alpha
Classifier: Topic :: Scientific/Engineering
Classifier: Topic :: Scientific/Engineering :: Electronic Design Automation (EDA)
Classifier: Programming Language :: Python :: 3
Requires-Python: >=3.7
Requires-Dist: toml>=0.10
Requires-Dist: klayout>=0.27.3
Requires-Dist: numpy>=1.0
Requires-Dist: networkx>=2.5
Requires-Dist: scipy>=1.5
Requires-Dist: liberty-parser>=0.0.19
Requires-Dist: pysmt>=0.9
Requires-Dist: z3-solver>=4.8
